fmi_weather_client/__init__.py
fmi_weather_client/errors.py
fmi_weather_client/http.py
fmi_weather_client/models.py
fmi_weather_client/parsers/__init__.py
fmi_weather_client/parsers/forecast.py
fmi_weather_client-0.7.2.dist-info/licenses/LICENSE
fmi_weather_client-0.7.2.dist-info/METADATA
fmi_weather_client-0.7.2.dist-info/WHEEL
fmi_weather_client-0.7.2.dist-info/top_level.txt
fmi_weather_client-0.7.2.dist-info/RECORD
