Metadata-Version: 2.4
Name: fmi-weather-client
Version: 0.7.2
Summary: Library for fetching weather information from Finnish Meteorological Institute (FMI)
Home-page: https://codeberg.org/saaste/fmi-weather-client
Author: Saaste
Author-email: saaste@gmail.com
Classifier: Programming Language :: Python :: 3.9
Classifier: Programming Language :: Python :: 3.10
Classifier: Programming Language :: Python :: 3.11
Classifier: Programming Language :: Python :: 3.12
Classifier: Programming Language :: Python :: 3.13
Classifier: License :: OSI Approved :: GNU General Public License v3 (GPLv3)
Classifier: Operating System :: OS Independent
Requires-Python: >=3.9.20
License-File: LICENSE
Requires-Dist: requests~=2.32
Requires-Dist: xmltodict~=0.15.1
Dynamic: author
Dynamic: author-email
Dynamic: classifier
Dynamic: description
Dynamic: description-content-type
Dynamic: home-page
Dynamic: license-file
Dynamic: requires-dist
Dynamic: requires-python
Dynamic: summary
